simcon/__init__.py
simcon/_native.cp39-win_amd64.pdb
simcon/_native.cp39-win_amd64.pyd
simcon/_native.pyi
simcon/base.py
simcon/events.py
simcon/utils.py
simcon/data/__init__.py
simcon/data/types.py
simcon-0.6.1.dist-info/LICENSE
simcon-0.6.1.dist-info/METADATA
simcon-0.6.1.dist-info/WHEEL
simcon-0.6.1.dist-info/top_level.txt
simcon-0.6.1.dist-info/RECORD
