Metadata-Version: 2.1
Name: simcon
Version: 0.6.1
Summary: MSFS SimConnect wrapper for Python
Home-page: https://gitlab.com/nARNcheg/py-simcon
Author: Roman Andriadi
Author-email: simcon@narn.me
License: UNKNOWN
Platform: UNKNOWN
Classifier: Operating System :: Microsoft :: Windows
Classifier: License :: OSI Approved :: Mozilla Public License 2.0 (MPL 2.0)
Classifier: Programming Language :: Python :: 3
Classifier: Topic :: Games/Entertainment
Classifier: Typing :: Typed
Requires-Python: >=3.7
